gpu4pyscf/__config__.py
gpu4pyscf/_patch_pyscf.py
gpu4pyscf/__init__.py
gpu4pyscf/gto/int3c1e.py
gpu4pyscf/gto/ecp.py
gpu4pyscf/gto/mole.py
gpu4pyscf/gto/int3c1e_ipip.py
gpu4pyscf/gto/int3c1e_ip.py
gpu4pyscf/gto/__init__.py
gpu4pyscf/hessian/rhf.py
gpu4pyscf/hessian/uks.py
gpu4pyscf/hessian/rks.py
gpu4pyscf/hessian/dispersion.py
gpu4pyscf/hessian/__init__.py
gpu4pyscf/hessian/uhf.py
gpu4pyscf/pop/esp.py
gpu4pyscf/pop/__init__.py
gpu4pyscf/df/df_jk.py
gpu4pyscf/df/df.py
gpu4pyscf/df/int3c2e.py
gpu4pyscf/df/j_engine_3c2e.py
gpu4pyscf/df/__init__.py
gpu4pyscf/df/cderi.py
gpu4pyscf/df/int3c2e_bdiv.py
gpu4pyscf/df/hessian/rhf.py
gpu4pyscf/df/hessian/jk.py
gpu4pyscf/df/hessian/uks.py
gpu4pyscf/df/hessian/rks.py
gpu4pyscf/df/hessian/__init__.py
gpu4pyscf/df/hessian/uhf.py
gpu4pyscf/df/grad/tdrks.py
gpu4pyscf/df/grad/tduhf.py
gpu4pyscf/df/grad/tdrks_ris.py
gpu4pyscf/df/grad/rhf.py
gpu4pyscf/df/grad/jk.py
gpu4pyscf/df/grad/uks.py
gpu4pyscf/df/grad/rks.py
gpu4pyscf/df/grad/tdrhf.py
gpu4pyscf/df/grad/__init__.py
gpu4pyscf/df/grad/uhf.py
gpu4pyscf/df/grad/tduks.py
gpu4pyscf/df/nac/tdrks.py
gpu4pyscf/df/nac/tdrks_ris.py
gpu4pyscf/df/nac/tdrhf.py
gpu4pyscf/df/nac/__init__.py
gpu4pyscf/lib/libgvhf_md.so
gpu4pyscf/lib/logger.py
gpu4pyscf/lib/libgvhf_rys.so
gpu4pyscf/lib/memcpy.py
gpu4pyscf/lib/cublas.py
gpu4pyscf/lib/libsolvent.so
gpu4pyscf/lib/libgecp.so
gpu4pyscf/lib/utils.py
gpu4pyscf/lib/libgdft.so
gpu4pyscf/lib/libmgrid.so
gpu4pyscf/lib/cupy_helper.py
gpu4pyscf/lib/cutensor.py
gpu4pyscf/lib/libgint_rys.so
gpu4pyscf/lib/libgint.so
gpu4pyscf/lib/cusolver.py
gpu4pyscf/lib/libmgrid_v2.so
gpu4pyscf/lib/libcupy_helper.so
gpu4pyscf/lib/multi_gpu.py
gpu4pyscf/lib/diis.py
gpu4pyscf/lib/__init__.py
gpu4pyscf/lib/libgvhf.so
gpu4pyscf/lib/libpbc.so
gpu4pyscf/properties/eda.py
gpu4pyscf/properties/polarizability.py
gpu4pyscf/properties/raman.py
gpu4pyscf/properties/ir.py
gpu4pyscf/properties/shielding.py
gpu4pyscf_cuda11x-1.5.2.dist-info/WHEEL
gpu4pyscf_cuda11x-1.5.2.dist-info/top_level.txt
gpu4pyscf_cuda11x-1.5.2.dist-info/METADATA
gpu4pyscf_cuda11x-1.5.2.dist-info/RECORD
gpu4pyscf_cuda11x-1.5.2.dist-info/licenses/LICENSE
